aiearth/openapi/__init__.py
aiearth/openapi/enums.py
aiearth/openapi/oss.py
aiearth/openapi/utils.py
aiearth/openapi/client/__init__.py
aiearth/openapi/client/_publisher.py
aiearth/openapi/client/_utils.py
aiearth/openapi/client/aieseg_client.py
aiearth/openapi/client/imagepublisher_client.py
aiearth/openapi/example/__init__.py
aiearth/openapi/models/__init__.py
aiearth/openapi/models/aieseg.py
aiearth/openapi/models/commons.py
aiearth/openapi/models/imagepublish.py
aiearth_openapi-1.3.0.dist-info/LICENSE
aiearth_openapi-1.3.0.dist-info/METADATA
aiearth_openapi-1.3.0.dist-info/WHEEL
aiearth_openapi-1.3.0.dist-info/top_level.txt
aiearth_openapi-1.3.0.dist-info/RECORD
