Metadata-Version: 2.1
Name: aiearth-openapi
Version: 1.3.0
Summary: AIEarth Engine Python SDK OpenAPI
Home-page: https://engine-aiearth.aliyun.com/
Author: AI Earth developer team
Author-email: aiearth@service.aliyun.com
License: APACHE LICENSE, VERSION 2.0
Requires-Python: >=3.8.0
License-File: LICENSE
Requires-Dist: alibabacloud-aiearth-engine20220609 (>=1.0.5)
Requires-Dist: imagesize (~=1.4.1)
Requires-Dist: numpy (~=1.24.3)
Requires-Dist: requests (~=2.31.0)
Requires-Dist: opencv-python (~=4.8.0.74)
Requires-Dist: matplotlib (~=3.7.1)
Requires-Dist: pillow (~=9.5.0)
Requires-Dist: tqdm (~=4.65.0)
Requires-Dist: oss2 (~=2.18.0)
Requires-Dist: aiearth-core (>=1.0.3)
